hacs_core/__init__.py
hacs_core/auth.py
hacs_core/clinical_reasoning.py
hacs_core/config.py
hacs_core/exceptions.py
hacs_core/mixins.py
hacs_core/persistence_protocols.py
hacs_core/protocol_utils.py
hacs_core/protocols.py
hacs_core/py.typed
hacs_core/tool_protocols.py
hacs_core/models/__init__.py
hacs_core-0.4.3.dist-info/METADATA
hacs_core-0.4.3.dist-info/WHEEL
hacs_core-0.4.3.dist-info/RECORD
