Metadata-Version: 2.4
Name: hacs-core
Version: 0.4.3
Summary: Core models and base classes for Healthcare Agent Communication Standard
Project-URL: Homepage, https://github.com/solanovisitor/hacs-ai
Project-URL: Documentation, https://github.com/solanovisitor/hacs-ai/blob/main/docs/
Project-URL: Repository, https://github.com/solanovisitor/hacs-ai
Project-URL: Issues, https://github.com/solanovisitor/hacs-ai/issues
Project-URL: Changelog, https://github.com/solanovisitor/hacs-ai/blob/main/CHANGELOG.md
Author-email: Solano Todeschini <solanovisitor@gmail.com>
Maintainer-email: Solano Todeschini <solanovisitor@gmail.com>
License: MIT
Keywords: actor,agents,ai,base-classes,core,evidence,healthcare,memory,models
Classifier: Development Status :: 4 - Beta
Classifier: Intended Audience :: Developers
Classifier: Intended Audience :: Healthcare Industry
Classifier: License :: OSI Approved :: MIT License
Classifier: Programming Language :: Python :: 3
Classifier: Programming Language :: Python :: 3.11
Classifier: Programming Language :: Python :: 3.12
Classifier: Topic :: Scientific/Engineering :: Medical Science Apps.
Classifier: Topic :: Software Development :: Libraries :: Python Modules
Classifier: Typing :: Typed
Requires-Python: >=3.11
Requires-Dist: hacs-infrastructure>=0.4.3
Requires-Dist: hacs-models>=0.4.3
Requires-Dist: pydantic<3.0.0,>=2.11.7
Requires-Dist: pyjwt>=2.8.0
Provides-Extra: all
Requires-Dist: cryptography>=41.0.0; extra == 'all'
Provides-Extra: auth
Requires-Dist: cryptography>=41.0.0; extra == 'auth'
Provides-Extra: dev
Requires-Dist: black>=23.0.0; extra == 'dev'
Requires-Dist: mypy>=1.8.0; extra == 'dev'
Requires-Dist: pytest-cov>=4.0.0; extra == 'dev'
Requires-Dist: pytest>=7.0.0; extra == 'dev'
Requires-Dist: ruff>=0.4.0; extra == 'dev'
